gnocchi_nagios/perfdata_dispatcher.py
gnocchi_nagios/cli.py
gnocchi_nagios/opts.py
gnocchi_nagios/__init__.py
gnocchi_nagios/perfdata_processor.py
gnocchi_nagios/gnocchi_client.py
gnocchi_nagios/tests/base.py
gnocchi_nagios/tests/__init__.py
gnocchi_nagios/tests/test_gnocchi_nagios.py
gnocchi_nagios-1.1.1.dist-info/metadata.json
gnocchi_nagios-1.1.1.dist-info/entry_points.txt
gnocchi_nagios-1.1.1.dist-info/DESCRIPTION.rst
gnocchi_nagios-1.1.1.dist-info/top_level.txt
gnocchi_nagios-1.1.1.dist-info/METADATA
gnocchi_nagios-1.1.1.dist-info/WHEEL
gnocchi_nagios-1.1.1.dist-info/pbr.json
gnocchi_nagios-1.1.1.dist-info/RECORD
