Metadata-Version: 2.0
Name: gnocchi-nagios
Version: 1.1.1
Summary: Gnocchi-nagios allows to push Nagios perfdata to Gnocchi
Home-page: https://github.com/sileht/gnocchi-nagios
Author: Mehdi Abaakouk
Author-email: sileht@sileht.net
License: UNKNOWN
Platform: UNKNOWN
Classifier: Intended Audience :: Information Technology
Classifier: Intended Audience :: System Administrators
Classifier: License :: OSI Approved :: Apache Software License
Classifier: Operating System :: POSIX :: Linux
Classifier: Programming Language :: Python
Classifier: Programming Language :: Python :: 2
Classifier: Programming Language :: Python :: 2.7
Classifier: Programming Language :: Python :: 3
Classifier: Programming Language :: Python :: 3.5
Requires-Dist: pbr (>=1.6)
Requires-Dist: gnocchiclient (>=2.7.0)
Requires-Dist: oslo.cache (>=1.5.0)
Requires-Dist: oslo.config (>=3.14.0)
Requires-Dist: oslo.utils (>=3.18.0)
Requires-Dist: oslo.log (>=2.3.0)
Requires-Dist: oslo.serialization (>=1.4.0)
Requires-Dist: cotyledon (>=1.5.0)
Requires-Dist: six
Requires-Dist: tenacity (>=3.1.0)
